curriculum_model/__init__.py
curriculum_model/__main__.py
curriculum_model/_version.py
curriculum_model/cli/__init__.py
curriculum_model/cli/copy.py
curriculum_model/db/__init__.py
curriculum_model/db/schema.py
curriculum_model/db/schema/__init__.py
curriculum_model/db/schema/views.py
tests/__init__.py
tests/test_schema.py
curriculum_model-0.1.0.dist-info/LICENSE
curriculum_model-0.1.0.dist-info/METADATA
curriculum_model-0.1.0.dist-info/WHEEL
curriculum_model-0.1.0.dist-info/entry_points.txt
curriculum_model-0.1.0.dist-info/top_level.txt
curriculum_model-0.1.0.dist-info/RECORD
