Metadata-Version: 2.1
Name: curriculum-model
Version: 0.1.0
Summary: Modelling HE curriculum delivery.
Home-page: https://github.com/jehboyes/curriculum_model
Author: James Boyes
Author-email: James.Boyes@lcm.ac.uk
License: UNKNOWN
Platform: UNKNOWN
